{
  "prices": {
    "gold": {
      "price_per_gram_inr": 13729.97,
      "price_usd_oz": 4490.68,
      "change_percent": 0.13,
      "change_value_usd": 5.62,
      "price_per_10g_inr": 137299.72
    },
    "silver": {
      "price_per_gram_inr": 230.62,
      "price_usd_oz": 75.43,
      "change_percent": 0.76,
      "change_value_usd": 0.56,
      "price_per_kg_inr": 230616.62
    },
    "platinum": {
      "price_per_gram_inr": 5931.28,
      "price_usd_oz": 1939.95,
      "change_percent": 0.6,
      "change_value_usd": 11.64
    },
    "currencies": {
      "USD_INR": 95.0971,
      "EUR_INR": 110.6295,
      "GBP_INR": 127.9391,
      "JPY_INR": 0.5958,
      "CHF_INR": 120.9887,
      "AUD_INR": 68.1358,
      "CAD_INR": 68.7465,
      "SGD_INR": 74.3876
    },
    "gold_silver_ratio": 59.54,
    "timestamp": "2026-06-02T17:04:03.381046",
    "source": "GoldAPI"
  },
  "timestamp": "2026-06-02T17:04:03.381930"
}